CHANGES.txt
MANIFEST.in
README.txt
setup.cfg
setup.py
docs/FAQ.txt
paw/__init__.py
paw/paw.py
paw.egg-info/PKG-INFO
paw.egg-info/SOURCES.txt
paw.egg-info/dependency_links.txt
paw.egg-info/requires.txt
paw.egg-info/top_level.txt