Metadata-Version: 1.1
Name: paw
Version: 0.0.1
Summary: A python package than can be used as a model/template for writing, testing and deploying python packages.
Home-page: https://github.com/baojie/paw.git
Author: Jie Bao
Author-email: baojie@gmail.com
License: License :: OSI Approved :: Python Software Foundation License
Platform: UNKNOWN
Classifier: Development Status :: 1 - Planning
Classifier: Intended Audience :: Developers
Classifier: Intended Audience :: System Administrators
Classifier: License :: OSI Approved :: Python Software Foundation License
Classifier: Programming Language :: Python
Classifier: Programming Language :: Python :: 2
Classifier: Programming Language :: Python :: 3
Classifier: Topic :: Software Development :: Libraries :: Python Modules
Classifier: Topic :: System :: Systems Administration :: Authentication/Directory
